{
  "hyperwebjs": {
    "total": 3223,
    "packages": {
      "create-hyperweb-app": 626,
      "@hyperweb/cli": 125,
      "hyperwebjs": 1435,
      "hyperweb-kit": 124,
      "@hyperweb/build": 650,
      "@hyperweb/ts-json-schema": 263
    }
  },
  "interchain-js": {
    "total": 158885,
    "packages": {
      "interchainjs": 20135,
      "injectivejs": 7221,
      "@interchainjs/utils": 22506,
      "@interchainjs/types": 22845,
      "@interchainjs/auth": 19426,
      "@interchainjs/cosmos": 20760,
      "@interchainjs/cosmos-msgs": 384,
      "@interchainjs/cosmos-query": 379,
      "@interchainjs/ethereum": 7374,
      "@interchainjs/injective": 8245,
      "@interchainjs/cosmos-types": 22886,
      "@interchainjs/ethermint": 796,
      "injective-query": 93,
      "injective-react": 2576,
      "injective-vue": 2240,
      "interchain-react": 1019
    }
  },
  "cosmos-kit": {
    "total": 1671579,
    "packages": {
      "interchain-kit": 6789,
      "@interchain-kit/core": 17254,
      "@interchain-kit/react": 6641,
      "@interchain-kit/vue": 1831,
      "cosmos-kit": 53450,
      "@cosmos-kit/core": 705652,
      "@cosmos-kit/react": 157375,
      "@cosmos-kit/react-lite": 190774,
      "@cosmos-kit/walletconnect": 531813
    }
  },
  "create-cosmos-app": {
    "total": 7175,
    "packages": {
      "create-cosmos-app": 5953,
      "create-interchain-app": 1222
    }
  },
  "interchain-kit": {
    "total": 32515,
    "packages": {
      "interchain-kit": 6789,
      "@interchain-kit/core": 17254,
      "@interchain-kit/react": 6641,
      "@interchain-kit/vue": 1831
    }
  },
  "interchain-kit-wallets": {
    "total": 85954,
    "packages": {
      "@interchain-kit/okx-extension": 9688,
      "@interchain-kit/mock-wallet": 4717,
      "@interchain-kit/leap-extension": 9886,
      "@interchain-kit/ledger": 5603,
      "@interchain-kit/coin98-extension": 5741,
      "@interchain-kit/leap-mobile": 5683,
      "@interchain-kit/keplr-mobile": 5553,
      "@interchain-kit/keplr-extension": 10244,
      "@interchain-kit/frontier-extension": 4009,
      "@interchain-kit/station-extension": 3980,
      "@interchain-kit/cosmostation-extension": 3980,
      "@interchain-kit/galaxy-station-extension": 4053,
      "@interchain-kit/vue": 1831,
      "@interchain-kit/cosmos-extension-metamask": 3396,
      "@interchain-kit/trust-extension": 2716,
      "@interchain-kit/leap-cosmos-extension-metamask": 3278,
      "@interchain-kit/xdefi-extension": 1596
    }
  },
  "cosmos-kit-wallets": {
    "total": 9254024,
    "packages": {
      "@interchain-kit/okx-extension": 9688,
      "@interchain-kit/mock-wallet": 4717,
      "@interchain-kit/leap-extension": 9886,
      "@interchain-kit/ledger": 5603,
      "@interchain-kit/coin98-extension": 5741,
      "@interchain-kit/leap-mobile": 5683,
      "@interchain-kit/keplr-mobile": 5553,
      "@interchain-kit/keplr-extension": 10244,
      "@interchain-kit/frontier-extension": 4009,
      "@interchain-kit/station-extension": 3980,
      "@interchain-kit/cosmostation-extension": 3980,
      "@interchain-kit/galaxy-station-extension": 4053,
      "@interchain-kit/vue": 1831,
      "@interchain-kit/cosmos-extension-metamask": 3396,
      "@interchain-kit/trust-extension": 2716,
      "@interchain-kit/leap-cosmos-extension-metamask": 3278,
      "@interchain-kit/xdefi-extension": 1596,
      "@cosmos-kit/frontier-extension": 59143,
      "@cosmos-kit/ledger": 68943,
      "@cosmos-kit/cosmos-extension-metamask": 44819,
      "@cosmos-kit/fin": 63088,
      "@cosmos-kit/coin98-extension": 64864,
      "@cosmos-kit/okxwallet-extension": 379245,
      "@cosmos-kit/trust-mobile": 342415,
      "@cosmos-kit/shell": 61272,
      "@cosmos-kit/leap-capsule-social-login": 5864,
      "@cosmos-kit/cosmostation-extension": 446312,
      "@cosmos-kit/vectis": 71471,
      "@cosmos-kit/fin-extension": 67427,
      "@cosmos-kit/ninji": 11401,
      "@cosmos-kit/station-extension": 372581,
      "@cosmos-kit/coin98": 65254,
      "@cosmos-kit/leap-extension": 500064,
      "@cosmos-kit/exodus": 59570,
      "@cosmos-kit/trust-extension": 333077,
      "@cosmos-kit/leap": 480214,
      "@cosmos-kit/xdefi": 368576,
      "@cosmos-kit/web3auth": 25532,
      "@cosmos-kit/initia-extension": 5819,
      "@cosmos-kit/cosmostation": 425232,
      "@cosmos-kit/shell-extension": 61881,
      "@cosmos-kit/cosmostation-mobile": 420901,
      "@cosmos-kit/vectis-extension": 70621,
      "@cosmos-kit/station": 372098,
      "@cosmos-kit/exodus-extension": 60816,
      "@cosmos-kit/leap-mobile": 471026,
      "@cosmos-kit/initia": 5383,
      "@cosmos-kit/frontier": 58261,
      "@cosmos-kit/trust": 341406,
      "@cosmos-kit/compass": 67417,
      "@cosmos-kit/keplr-mobile": 496324,
      "@cosmos-kit/keplr-extension": 517954,
      "@cosmos-kit/ninji-extension": 12222,
      "@cosmos-kit/compass-extension": 72560,
      "@cosmos-kit/xdefi-extension": 384462,
      "@cosmos-kit/okxwallet": 335178,
      "@cosmos-kit/omni": 68651,
      "@cosmos-kit/keplr": 496581,
      "@cosmos-kit/omni-mobile": 70556,
      "@cosmos-kit/leap-metamask-cosmos-snap": 461589
    }
  },
  "cosmwasm": {
    "total": 2052782,
    "packages": {
      "@cosmwasm/ts-codegen": 1001696,
      "@cosmwasm/ts-codegen-types": 45734,
      "@cosmwasm/ts-codegen-ast": 46453,
      "wasm-ast-types": 953132,
      "cosmwasm-typescript-gen": 5767
    }
  },
  "interchain-ui": {
    "total": 169929,
    "packages": {
      "@interchain-ui/react": 162304,
      "@interchain-ui/vue": 7625
    }
  },
  "telescope": {
    "total": 5705856,
    "packages": {
      "@cosmology/telescope": 441346,
      "@cosmology/lcd": 507297,
      "@cosmology/ast": 503986,
      "@cosmology/types": 695980,
      "@cosmology/utils": 696403,
      "@cosmology/proto-parser": 695563,
      "@osmonauts/telescope": 233329,
      "@osmonauts/lcd": 1016075,
      "@osmonauts/ast": 231038,
      "@osmonauts/utils": 219612,
      "@osmonauts/types": 232070,
      "@osmonauts/proto-parser": 233157
    }
  },
  "dydx": {
    "total": 212319,
    "packages": {
      "@dydxprotocol/v4-client-js": 212319
    }
  },
  "stargaze": {
    "total": 10437,
    "packages": {
      "stargazejs": 6805,
      "@stargaze-zone/chain": 945,
      "@stargaze-zone/contracts": 1095,
      "stargaze-query": 1592
    }
  },
  "stride": {
    "total": 21007,
    "packages": {
      "stridejs": 21007
    }
  },
  "quicksilver": {
    "total": 4502,
    "packages": {
      "quicksilverjs": 4502
    }
  },
  "juno": {
    "total": 19584,
    "packages": {
      "juno-network": 17783,
      "@juno-network/assets": 1801
    }
  },
  "osmosis": {
    "total": 373865,
    "packages": {
      "@osmonauts/math": 29731,
      "osmojs": 322764,
      "osmo-query": 21370
    }
  },
  "chain-registry": {
    "total": 6814945,
    "packages": {
      "@chain-registry/client": 633567,
      "@chain-registry/types": 2324749,
      "@chain-registry/keplr": 1023522,
      "@chain-registry/cosmostation": 827363,
      "@chain-registry/osmosis": 87987,
      "@chain-registry/juno": 41748,
      "@chain-registry/assets": 64731,
      "@chain-registry/utils": 805942,
      "chain-registry": 1005336
    }
  },
  "cosmology": {
    "total": 149861,
    "packages": {
      "cosmjs-utils": 20754,
      "@cosmology/cli": 7064,
      "@cosmology/core": 18370,
      "cosmology": 6810,
      "interchain": 68203,
      "interchain-query": 12468,
      "create-cosmos-app": 5953,
      "create-cosmwasm-app": 1257,
      "@cosmology-ui/react": 8982
    }
  },
  "starship": {
    "total": 27090,
    "packages": {
      "starshipjs": 10720,
      "@starship-ci/cli": 7902,
      "@starship-ci/client": 8468
    }
  },
  "launchql": {
    "total": null,
    "packages": {
      "@launchql/db-templates": 3573,
      "@launchql/db-transform": 1537,
      "@launchql/ext-achievements": 1865,
      "@launchql/ext-jobs-queue": 2310,
      "@launchql/ext-jwt-claims": 2043,
      "@launchql/ext-types": 2621,
      "@launchql/faker": 2244,
      "@launchql/inflection": 2250,
      "@launchql/totp": 2223,
      "@pgql/parse": 36721,
      "@pgsql/enums": 911,
      "@pgsql/parser": 16162,
      "@pgsql/types": 954509,
      "@pgsql/utils": 186480,
      "@pyramation/postgraphile-plugin-fulltext-filter": 47321,
      "graphile-column-privileges-mutations": 2999,
      "libpg-query": 2739601,
      "pg-proto-parser": 4768,
      "pg-query-native-latest": 342,
      "pg-utils": 620,
      "pgsql-deparser": 2173660,
      "pgsql-enums": 2192962,
      "pgsql-parser": 1996256
    }
  },
  "protobufs": {
    "total": 3229927,
    "packages": {
      "@protobufs/cosmos": 343127,
      "@protobufs/google": 356771,
      "@protobufs/gogoproto": 356487,
      "@protobufs/cosmwasm": 141031,
      "@protobufs/tendermint": 339831,
      "@protobufs/ibc": 144953,
      "@protobufs/cosmos_proto": 342325,
      "@protobufs/osmosis": 10506,
      "@protobufs/secret": 461,
      "@protobufs/juno": 1513,
      "@protobufs/akash": 556,
      "@protobufs/regen": 531,
      "@protobufs/pylons": 361,
      "@protobufs/stargaze": 584,
      "@protobufs/bcna": 457,
      "@protobufs/comdex": 394,
      "@protobufs/evmos": 296,
      "@protobufs/axelar": 259,
      "@protobufs/amino": 147537,
      "@cosmology/protobufjs": 819420,
      "@pyramation/protobufjs": 222527
    }
  },
  "utils": {
    "total": null,
    "packages": {
      "ast-stringify": 854095,
      "nested-obj": 231762,
      "schema-typescript": 12397,
      "etag-hash": 48532,
      "uuid-hash": 14443,
      "inquirerer": 871124,
      "publish-scripts": 15251,
      "skitch-template": 1355
    }
  }
}